diel_models/__init__.py
diel_models/biomass_adjuster.py
diel_models/day_night_creator.py
diel_models/diel_models_creator.py
diel_models/nitrate_uptake_ratio.py
diel_models/photon_reaction_inhibitor.py
diel_models/pipeline.py
diel_models/storage_pool_generator.py
diel_models-1.2.3.dist-info/LICENSE
diel_models-1.2.3.dist-info/METADATA
diel_models-1.2.3.dist-info/WHEEL
diel_models-1.2.3.dist-info/top_level.txt
diel_models-1.2.3.dist-info/RECORD
