Metadata-Version: 2.1
Name: diel_models
Version: 1.2.3
Summary: diel_models:
Author: Luciana Martins and João Capela
License: MIT
Keywords: plants,diel models
Platform: unix
Platform: linux
Platform: osx
Platform: cygwin
Platform: win32
Classifier: Programming Language :: Python :: 3
Classifier: Programming Language :: Python :: 3 :: Only
Classifier: Programming Language :: Python :: 3.8
Classifier: Programming Language :: Python :: 3.9
Classifier: Programming Language :: Python :: 3.10
Classifier: Programming Language :: Python :: 3.11
Classifier: Programming Language :: Python :: 3.12
Requires-Python: >=3.8
License-File: LICENSE
Requires-Dist: cobra
Provides-Extra: testing
Requires-Dist: pytest>=7.1.1; extra == "testing"
Requires-Dist: pytest-cov>=3.0.0; extra == "testing"
Requires-Dist: mypy>=0.942; extra == "testing"
Requires-Dist: flake8>=4.0.1; extra == "testing"
Requires-Dist: tox>=3.25.0; extra == "testing"
